simplemachinelearning/Class_Data_Explorer.py
simplemachinelearning/Class_Data_Loader.py
simplemachinelearning/Class_Data_Modeler.py
simplemachinelearning/Class_Data_Preprocessor.py
simplemachinelearning/__init__.py
simplemachinelearning-0.0.2.dist-info/METADATA
simplemachinelearning-0.0.2.dist-info/RECORD
simplemachinelearning-0.0.2.dist-info/WHEEL
simplemachinelearning-0.0.2.dist-info/top_level.txt
